LICENSE
prompt_matrix/__init__.py
prompt_matrix/prompt_matrix.py
prompt_matrix-0.1.4.dist-info/LICENSE
prompt_matrix-0.1.4.dist-info/METADATA
prompt_matrix-0.1.4.dist-info/WHEEL
prompt_matrix-0.1.4.dist-info/RECORD
